pysepm_evo/__init__.py
pysepm_evo/intelligibilityMeasures.py
pysepm_evo/qualityMeasures.py
pysepm_evo/reverberationMeasures.py
pysepm_evo/util.py
pysepm_evo-0.1.1.dist-info/LICENSE
pysepm_evo-0.1.1.dist-info/METADATA
pysepm_evo-0.1.1.dist-info/WHEEL
pysepm_evo-0.1.1.dist-info/top_level.txt
pysepm_evo-0.1.1.dist-info/RECORD
